[
    {
        "date": "2025-10-05T22:30:00.000Z",
        "teamA": "DSP Shows",
        "teamB": "Dianes Dipsticks",
        "goalieA": "Daniel Darnold",
        "goalieB": "Alex Chang"
    },
    {
        "date": "2025-10-06T00:00:00.000Z",
        "teamA": "Mansour Jewelers",
        "teamB": "Ice Cream Bar",
        "goalieA": "Matt Hobbs",
        "goalieB": "Derrick Tomberelli"
    },
    {
        "date": "2025-10-06T01:30:00.000Z",
        "teamA": "Orcutt Real Estate",
        "teamB": "Instant Replay",
        "goalieA": "Dylan Riker",
        "goalieB": "Rich Ford"
    },
    {
        "date": "2025-10-07T01:15:00.000Z",
        "teamA": "Ice Cream Bar",
        "teamB": "Mansour Jewelers",
        "goalieA": "Matt Hobbs",
        "goalieB": "Alton Pace"
    },
    {
        "date": "2025-10-09T01:15:00.000Z",
        "teamA": "Dianes Dipsticks",
        "teamB": "Instant Replay",
        "goalieA": "Alex Chang",
        "goalieB": "Rich Ford"
    },
    {
        "date": "2025-10-12T22:30:00.000Z",
        "teamA": "Orcutt Real Estate",
        "teamB": "DSP Shows",
        "goalieA": "Daniel Darnold",
        "goalieB": "Alex Chang"
    },
    {
        "date": "2025-10-13T00:00:00.000Z",
        "teamA": "Orcutt Real Estate",
        "teamB": "Mansour Jewelers",
        "goalieA": "Derrick Tomberelli",
        "goalieB": "Matt Hobbs"
    },
    {
        "date": "2025-10-13T01:30:00.000Z",
        "teamA": "Dianes Dipsticks",
        "teamB": "Ice Cream Bar",
        "goalieA": "Dylan Riker",
        "goalieB": "Rich Ford"
    },
    {
        "date": "2025-10-14T01:15:00.000Z",
        "teamA": "DSP Shows",
        "teamB": "Ice Cream Bar",
        "goalieA": "Matt Hobbs",
        "goalieB": "Alton Pace"
    },
    {
        "date": "2025-10-16T01:15:00.000Z",
        "teamA": "Orcutt Real Estate",
        "teamB": "Mansour Jewelers",
        "goalieA": "Alex Chang",
        "goalieB": "Rich Ford"
    },
    {
        "date": "2025-10-19T22:30:00.000Z",
        "teamA": "DSP Shows",
        "teamB": "Ice Cream Bar",
        "goalieA": "Daniel Darnold",
        "goalieB": "Derrick Tomberelli"
    },
    {
        "date": "2025-10-20T00:00:00.000Z",
        "teamA": "Instant Replay",
        "teamB": "Orcutt Real Estate",
        "goalieA": "Alex Chang",
        "goalieB": "Matt Hobbs"
    },
    {
        "date": "2025-10-20T01:30:00.000Z",
        "teamA": "Mansour Jewelers",
        "teamB": "Dianes Dipsticks",
        "goalieA": "Rich Ford",
        "goalieB": "Dylan Riker"
    },
    {
        "date": "2025-10-21T01:15:00.000Z",
        "teamA": "Instant Replay",
        "teamB": "Ice Cream Bar",
        "goalieA": "Derrick Tomberelli",
        "goalieB": "Matt Hobbs"
    },
    {
        "date": "2025-10-23T01:15:00.000Z",
        "teamA": "Mansour Jewelers",
        "teamB": "Instant Replay",
        "goalieA": "Alex Chang",
        "goalieB": "Rich Ford"
    },
    {
        "date": "2025-10-26T22:30:00.000Z",
        "teamA": "Orcutt Real Estate",
        "teamB": "Mansour Jewelers",
        "goalieA": "Daniel Darnold",
        "goalieB": "Derrick Tomberelli"
    },
    {
        "date": "2025-10-27T00:00:00.000Z",
        "teamA": "DSP Shows",
        "teamB": "Instant Replay",
        "goalieA": "Alex Chang",
        "goalieB": "Matt Hobbs"
    },
    {
        "date": "2025-10-27T01:30:00.000Z",
        "teamA": "Ice Cream Bar",
        "teamB": "Dianes Dipsticks",
        "goalieA": "Rich Ford",
        "goalieB": "Dylan Riker"
    },
    {
        "date": "2025-10-28T01:15:00.000Z",
        "teamA": "DSP Shows",
        "teamB": "Mansour Jewelers",
        "goalieA": "Derrick Tomberelli",
        "goalieB": "Matt Hobbs"
    },
    {
        "date": "2025-10-30T01:15:00.000Z",
        "teamA": "Orcutt Real Estate",
        "teamB": "Mansour Jewelers",
        "goalieA": "Alex Chang",
        "goalieB": "Rich Ford"
    },
    {
        "date": "2025-11-02T23:30:00.000Z",
        "teamA": "Ice Cream Bar",
        "teamB": "DSP Shows",
        "goalieA": "Daniel Darnold",
        "goalieB": "Alex Chang"
    },
    {
        "date": "2025-11-03T01:00:00.000Z",
        "teamA": "Dianes Dipsticks",
        "teamB": "Mansour Jewelers",
        "goalieA": "Derrick Tomberelli",
        "goalieB": "Matt Hobbs"
    },
    {
        "date": "2025-11-03T02:30:00.000Z",
        "teamA": "Instant Replay",
        "teamB": "Orcutt Real Estate",
        "goalieA": "Rich Ford",
        "goalieB": "Dylan Riker"
    },
    {
        "date": "2025-11-04T02:15:00.000Z",
        "teamA": "Dianes Dipsticks",
        "teamB": "Ice Cream Bar",
        "goalieA": "Alton Pace",
        "goalieB": "Matt Hobbs"
    },
    {
        "date": "2025-11-06T02:15:00.000Z",
        "teamA": "Mansour Jewelers",
        "teamB": "Instant Replay",
        "goalieA": "Alex Chang",
        "goalieB": "Rich Ford"
    },
    {
        "date": "2025-11-09T23:30:00.000Z",
        "teamA": "Dianes Dipsticks",
        "teamB": "DSP Shows",
        "goalieA": "Daniel Darnold",
        "goalieB": "Alex Chang"
    },
    {
        "date": "2025-11-10T01:00:00.000Z",
        "teamA": "Mansour Jewelers",
        "teamB": "Ice Cream Bar",
        "goalieA": "Derrick Tomberelli",
        "goalieB": "Matt Hobbs"
    },
    {
        "date": "2025-11-10T02:30:00.000Z",
        "teamA": "Orcutt Real Estate",
        "teamB": "Instant Replay",
        "goalieA": "Rich Ford",
        "goalieB": "Dylan Riker"
    },
    {
        "date": "2025-11-11T02:15:00.000Z",
        "teamA": "Mansour Jewelers",
        "teamB": "DSP Shows",
        "goalieA": "Alton Pace",
        "goalieB": "Matt Hobbs"
    },
    {
        "date": "2025-11-13T02:15:00.000Z",
        "teamA": "Dianes Dipsticks",
        "teamB": "Instant Replay",
        "goalieA": "Alex Chang",
        "goalieB": "Rich Ford"
    },
    {
        "date": "2025-11-16T23:30:00.000Z",
        "teamA": "Ice Cream Bar",
        "teamB": "Dianes Dipsticks",
        "goalieA": "Daniel Darnold",
        "goalieB": "??"
    },
    {
        "date": "2025-11-17T01:00:00.000Z",
        "teamA": "Mansour Jewelers",
        "teamB": "Instant Replay",
        "goalieA": "Derrick Tomberelli",
        "goalieB": "Matt Hobbs"
    },
    {
        "date": "2025-11-17T02:30:00.000Z",
        "teamA": "DSP Shows",
        "teamB": "Orcutt Real Estate",
        "goalieA": "Rich Ford",
        "goalieB": "Dylan Riker"
    },
    {
        "date": "2025-11-18T02:15:00.000Z",
        "teamA": "Instant Replay",
        "teamB": "Ice Cream Bar",
        "goalieA": "Alton Pace",
        "goalieB": "Matt Hobbs"
    },
    {
        "date": "2025-11-20T02:15:00.000Z",
        "teamA": "Instant Replay",
        "teamB": "Dianes Dipsticks",
        "goalieA": "??",
        "goalieB": "Rich Ford"
    },
    {
        "date": "2025-11-23T23:30:00.000Z",
        "teamA": "Orcutt Real Estate",
        "teamB": "Dianes Dipsticks",
        "goalieA": "Daniel Darnold",
        "goalieB": "??"
    },
    {
        "date": "2025-11-24T01:00:00.000Z",
        "teamA": "Ice Cream Bar",
        "teamB": "Mansour Jewelers",
        "goalieA": "Derrick Tomberelli",
        "goalieB": "Matt Hobbs"
    },
    {
        "date": "2025-11-24T02:30:00.000Z",
        "teamA": "Instant Replay",
        "teamB": "DSP Shows",
        "goalieA": "Rich Ford",
        "goalieB": "Dylan Riker"
    },
    {
        "date": "2025-12-02T02:15:00.000Z",
        "teamA": "Ice Cream Bar",
        "teamB": "Instant Replay",
        "goalieA": "Alton Pace",
        "goalieB": "Matt Hobbs"
    },
    {
        "date": "2025-12-04T02:15:00.000Z",
        "teamA": "Instant Replay",
        "teamB": "Orcutt Real Estate",
        "goalieA": "Alex Chang",
        "goalieB": "Rich Ford"
    },
    {
        "date": "2025-12-07T23:30:00.000Z",
        "teamA": "Instant Replay",
        "teamB": "Ice Cream Bar",
        "goalieA": "Daniel Darnold",
        "goalieB": "Alex Chang"
    },
    {
        "date": "2025-12-08T01:00:00.000Z",
        "teamA": "Mansour Jewelers",
        "teamB": "Dianes Dipsticks",
        "goalieA": "Derrick Tomberelli",
        "goalieB": "Matt Hobbs"
    },
    {
        "date": "2025-12-08T02:30:00.000Z",
        "teamA": "Orcutt Real Estate",
        "teamB": "DSP Shows",
        "goalieA": "Rich Ford",
        "goalieB": "Dylan Riker"
    },
    {
        "date": "2025-12-09T02:15:00.000Z",
        "teamA": "Orcutt Real Estate",
        "teamB": "Ice Cream Bar",
        "goalieA": "Alton Pace",
        "goalieB": "Matt Hobbs"
    },
    {
        "date": "2025-12-11T02:15:00.000Z",
        "teamA": "Instant Replay",
        "teamB": "DSP Shows",
        "goalieA": "Alex Chang",
        "goalieB": "Rich Ford"
    },
    {
        "date": "2025-12-14T23:30:00.000Z",
        "teamA": "DSP Shows",
        "teamB": "Orcutt Real Estate",
        "goalieA": "Daniel Darnold",
        "goalieB": "Alex Chang"
    },
    {
        "date": "2025-12-15T01:00:00.000Z",
        "teamA": "Ice Cream Bar",
        "teamB": "Dianes Dipsticks",
        "goalieA": "Derrick Tomberelli",
        "goalieB": "Matt Hobbs"
    },
    {
        "date": "2025-12-15T02:30:00.000Z",
        "teamA": "Mansour Jewelers",
        "teamB": "Instant Replay",
        "goalieA": "Rich Ford",
        "goalieB": "Dylan Riker"
    },
    {
        "date": "2025-12-16T02:15:00.000Z",
        "teamA": "DSP Shows",
        "teamB": "Dianes Dipsticks",
        "goalieA": "Alton Pace",
        "goalieB": "Matt Hobbs"
    },
    {
        "date": "2025-12-18T02:15:00.000Z",
        "teamA": "Ice Cream Bar",
        "teamB": "Dianes Dipsticks",
        "goalieA": "Alex Chang",
        "goalieB": "Rich Ford"
    },
    {
        "date": "2025-12-21T23:30:00.000Z",
        "teamA": "DSP Shows",
        "teamB": "Dianes Dipsticks",
        "goalieA": "Daniel Darnold",
        "goalieB": "Alex Chang"
    },
    {
        "date": "2025-12-22T01:00:00.000Z",
        "teamA": "Dianes Dipsticks",
        "teamB": "Orcutt Real Estate",
        "goalieA": "Derrick Tomberelli",
        "goalieB": "Matt Hobbs"
    },
    {
        "date": "2025-12-22T02:30:00.000Z",
        "teamA": "Ice Cream Bar",
        "teamB": "Mansour Jewelers",
        "goalieA": "Rich Ford",
        "goalieB": "Dylan Riker"
    },
    {
        "date": "2026-01-04T23:30:00.000Z",
        "teamA": "DSP Shows",
        "teamB": "Ice Cream Bar",
        "goalieA": "Daniel Darnold",
        "goalieB": "Alex Chang"
    },
    {
        "date": "2026-01-05T01:00:00.000Z",
        "teamA": "DSP Shows",
        "teamB": "Mansour Jewelers",
        "goalieA": "Derrick Tomberelli",
        "goalieB": "Matt Hobbs"
    },
    {
        "date": "2026-01-05T02:30:00.000Z",
        "teamA": "Orcutt Real Estate",
        "teamB": "Dianes Dipsticks",
        "goalieA": "Rich Ford",
        "goalieB": "Dylan Riker"
    },
    {
        "date": "2026-01-06T02:15:00.000Z",
        "teamA": "Dianes Dipsticks",
        "teamB": "Orcutt Real Estate",
        "goalieA": "Alton Pace",
        "goalieB": "Matt Hobbs"
    },
    {
        "date": "2026-01-08T02:15:00.000Z",
        "teamA": "DSP Shows",
        "teamB": "Mansour Jewelers",
        "goalieA": "Alex Chang",
        "goalieB": "Rich Ford"
    },
    {
        "date": "2026-01-11T23:30:00.000Z",
        "teamA": "Ice Cream Bar",
        "teamB": "DSP Shows",
        "goalieA": "Daniel Darnold",
        "goalieB": "Alex Chang"
    },
    {
        "date": "2026-01-12T01:00:00.000Z",
        "teamA": "Orcutt Real Estate",
        "teamB": "Ice Cream Bar",
        "goalieA": "Derrick Tomberelli",
        "goalieB": "Matt Hobbs"
    },
    {
        "date": "2026-01-12T02:30:00.000Z",
        "teamA": "Dianes Dipsticks",
        "teamB": "Mansour Jewelers",
        "goalieA": "Rich Ford",
        "goalieB": "Dylan Riker"
    },
    {
        "date": "2026-01-13T02:15:00.000Z",
        "teamA": "Mansour Jewelers",
        "teamB": "Orcutt Real Estate",
        "goalieA": "Alton Pace",
        "goalieB": "Matt Hobbs"
    },
    {
        "date": "2026-01-15T02:15:00.000Z",
        "teamA": "Dianes Dipsticks",
        "teamB": "DSP Shows",
        "goalieA": "Alex Chang",
        "goalieB": "Rich Ford"
    },
    {
        "date": "2026-01-18T23:30:00.000Z",
        "teamA": "Orcutt Real Estate",
        "teamB": "DSP Shows",
        "goalieA": "Daniel Darnold",
        "goalieB": "Alex Chang"
    },
    {
        "date": "2026-01-19T01:00:00.000Z",
        "teamA": "Orcutt Real Estate",
        "teamB": "Ice Cream Bar",
        "goalieA": "Derrick Tomberelli",
        "goalieB": "Matt Hobbs"
    },
    {
        "date": "2026-01-19T02:30:00.000Z",
        "teamA": "Dianes Dipsticks",
        "teamB": "Mansour Jewelers",
        "goalieA": "Rich Ford",
        "goalieB": "Dylan Riker"
    },
    {
        "date": "2026-01-20T02:15:00.000Z",
        "teamA": "DSP Shows",
        "teamB": "Mansour Jewelers",
        "goalieA": "Alton Pace",
        "goalieB": "Matt Hobbs"
    },
    {
        "date": "2026-01-22T02:15:00.000Z",
        "teamA": "Ice Cream Bar",
        "teamB": "Orcutt Real Estate",
        "goalieA": "Alex Chang",
        "goalieB": "Rich Ford"
    },
    {
        "date": "2026-01-25T23:30:00.000Z",
        "teamA": "Mansour Jewelers",
        "teamB": "Ice Cream Bar",
        "goalieA": "Daniel Darnold",
        "goalieB": "Alex Chang"
    },
    {
        "date": "2026-01-26T01:00:00.000Z",
        "teamA": "Dianes Dipsticks",
        "teamB": "Orcutt Real Estate",
        "goalieA": "Derrick Tomberelli",
        "goalieB": "Matt Hobbs"
    },
    {
        "date": "2026-01-26T02:30:00.000Z",
        "teamA": "DSP Shows",
        "teamB": "Instant Replay",
        "goalieA": "Rich Ford",
        "goalieB": "Dylan Riker"
    },
    {
        "date": "2026-01-27T02:15:00.000Z",
        "teamA": "Instant Replay",
        "teamB": "Dianes Dipsticks",
        "goalieA": "Alton Pace",
        "goalieB": "Matt Hobbs"
    },
    {
        "date": "2026-01-29T02:15:00.000Z",
        "teamA": "Ice Cream Bar",
        "teamB": "Orcutt Real Estate",
        "goalieA": "Alex Chang",
        "goalieB": "Rich Ford"
    },
    {
        "date": "2026-02-01T23:30:00.000Z",
        "teamA": "Ice Cream Bar",
        "teamB": "Instant Replay",
        "goalieA": "Daniel Darnold",
        "goalieB": "Alex Chang"
    },
    {
        "date": "2026-02-02T01:00:00.000Z",
        "teamA": "Dianes Dipsticks",
        "teamB": "DSP Shows",
        "goalieA": "Derrick Tomberelli",
        "goalieB": "Matt Hobbs"
    },
    {
        "date": "2026-02-02T02:30:00.000Z",
        "teamA": "Orcutt Real Estate",
        "teamB": "Mansour Jewelers",
        "goalieA": "Rich Ford",
        "goalieB": "Dylan Riker"
    },
    {
        "date": "2026-02-03T02:15:00.000Z",
        "teamA": "Dianes Dipsticks",
        "teamB": "Ice Cream Bar",
        "goalieA": "Alton Pace",
        "goalieB": "Matt Hobbs"
    },
    {
        "date": "2026-02-05T02:15:00.000Z",
        "teamA": "Instant Replay",
        "teamB": "DSP Shows",
        "goalieA": "Alex Chang",
        "goalieB": "Rich Ford"
    },
    {
        "date": "2026-02-10T02:15:00.000Z",
        "teamA": "DSP Shows",
        "teamB": "Mansour Jewelers",
        "goalieA": "Alton Pace",
        "goalieB": "Matt Hobbs"
    },
    {
        "date": "2026-02-12T02:15:00.000Z",
        "teamA": "Orcutt Real Estate",
        "teamB": "Instant Replay",
        "goalieA": "Alex Chang",
        "goalieB": "Rich Ford"
    },
    {
        "date": "2026-02-15T23:30:00.000Z",
        "teamA": "DSP Shows",
        "teamB": "Mansour Jewelers",
        "goalieA": "Daniel Darnold",
        "goalieB": "Alex Chang"
    },
    {
        "date": "2026-02-16T01:00:00.000Z",
        "teamA": "Dianes Dipsticks",
        "teamB": "Mansour Jewelers",
        "goalieA": "Derrick Tomberelli",
        "goalieB": "Matt Hobbs"
    },
    {
        "date": "2026-02-16T02:30:00.000Z",
        "teamA": "Orcutt Real Estate",
        "teamB": "Ice Cream Bar",
        "goalieA": "Rich Ford",
        "goalieB": "Dylan Riker"
    },
    {
        "date": "2026-02-17T02:15:00.000Z",
        "teamA": "Orcutt Real Estate",
        "teamB": "DSP Shows",
        "goalieA": "Alton Pace",
        "goalieB": "Matt Hobbs"
    },
    {
        "date": "2026-02-19T02:15:00.000Z",
        "teamA": "Dianes Dipsticks",
        "teamB": "Instant Replay",
        "goalieA": "Alex Chang",
        "goalieB": "Rich Ford"
    },
    {
        "date": "2026-02-22T23:30:00.000Z",
        "teamA": "Mansour Jewelers",
        "teamB": "Instant Replay",
        "goalieA": "Daniel Darnold",
        "goalieB": "Alex Chang"
    },
    {
        "date": "2026-02-23T01:00:00.000Z",
        "teamA": "Dianes Dipsticks",
        "teamB": "Orcutt Real Estate",
        "goalieA": "Derrick Tomberelli",
        "goalieB": "Matt Hobbs"
    },
    {
        "date": "2026-02-23T02:30:00.000Z",
        "teamA": "Ice Cream Bar",
        "teamB": "DSP Shows",
        "goalieA": "Rich Ford",
        "goalieB": "Dylan Riker"
    }
]